check_number_order/__init__.py
check_number_order/check_number_order.py
tests/__init__.py
tests/test_check_number_order.py
check_number_order-0.1.0.dist-info/LICENSE
check_number_order-0.1.0.dist-info/METADATA
check_number_order-0.1.0.dist-info/WHEEL
check_number_order-0.1.0.dist-info/top_level.txt
check_number_order-0.1.0.dist-info/RECORD
